[
    {
        "domain": ".example.com",
        "expirationDate": 1751781605.582259,
        "hostOnly": false,
        "httpOnly": false,
        "name": "_example_cookie",
        "path": "/",
        "sameSite": "unspecified",
        "secure": true,
        "session": false,
        "storeId": "0",
        "value": "example_value_1",
        "id": 1
    },
    {
        "domain": ".example.com",
        "expirationDate": 1720246503.828805,
        "hostOnly": false,
        "httpOnly": true,
        "name": "access_token",
        "path": "/",
        "sameSite": "strict",
        "secure": true,
        "session": false,
        "storeId": "0",
        "value": "example_value_2",
        "id": 2
    },
    {
        "domain": ".example.com",
        "expirationDate": 1720252800.545479,
        "hostOnly": false,
        "httpOnly": false,
        "name": "another_cookie",
        "path": "/",
        "sameSite": "unspecified",
        "secure": false,
        "session": false,
        "storeId": "0",
        "value": "example_value_3",
        "id": 3
    },
    {
        "domain": ".example.com",
        "expirationDate": 1754805605.747256,
        "hostOnly": false,
        "httpOnly": false,
        "name": "yet_another_cookie",
        "path": "/",
        "sameSite": "unspecified",
        "secure": false,
        "session": false,
        "storeId": "0",
        "value": "example_value_4",
        "id": 4
    },
    {
        "domain": ".example.com",
        "hostOnly": false,
        "httpOnly": false,
        "name": "session_cookie",
        "path": "/",
        "sameSite": "unspecified",
        "secure": true,
        "session": true,
        "storeId": "0",
        "value": "example_value_5",
        "id": 5
    },
    {
        "domain": ".example.com",
        "hostOnly": false,
        "httpOnly": true,
        "name": "secure_cookie",
        "path": "/",
        "sameSite": "unspecified",
        "secure": true,
        "session": true,
        "storeId": "0",
        "value": "example_value_6",
        "id": 6
    },
    {
        "domain": ".example.com",
        "expirationDate": 1720252801.58235,
        "hostOnly": false,
        "httpOnly": false,
        "name": "another_example_cookie",
        "path": "/",
        "sameSite": "unspecified",
        "secure": true,
        "session": false,
        "storeId": "0",
        "value": "example_value_7",
        "id": 7
    },
    {
        "domain": ".example.com",
        "expirationDate": 1720260003.582382,
        "hostOnly": false,
        "httpOnly": false,
        "name": "example_cookie_8",
        "path": "/",
        "sameSite": "unspecified",
        "secure": false,
        "session": false,
        "storeId": "0",
        "value": "example_value_8",
        "id": 8
    }
]
